tententgclib
