Metadata-Version: 2.1
Name: tententgclibrary
Version: 0.0.4
Summary: Mathematics calculate library
Home-page: UNKNOWN
Author: Thanyapisit Buaprakhong
Author-email: thanyapisit.bua@gmail.com
License: MIT
Keywords: tententgc
Platform: UNKNOWN
Classifier: Development Status :: 5 - Production/Stable
Classifier: Intended Audience :: Education
Classifier: Operating System :: Microsoft :: Windows :: Windows 10
Classifier: License :: OSI Approved :: MIT License
Classifier: Programming Language :: Python :: 3
License-File: LICENCE.txt
